datastep/__init__.py
datastep/constants.py
datastep/exceptions.py
datastep/file_utils.py
datastep/quilt_utils.py
datastep/step.py
datastep/bin/__init__.py
datastep/bin/make_new_step.py
datastep-0.1.9.dist-info/LICENSE
datastep-0.1.9.dist-info/METADATA
datastep-0.1.9.dist-info/WHEEL
datastep-0.1.9.dist-info/entry_points.txt
datastep-0.1.9.dist-info/top_level.txt
datastep-0.1.9.dist-info/RECORD
